freefall/__init__.py
freefall/falling_objects.py
freefall/simulators.py
freefall/utilities.py
freefall-1.0.0b1.dist-info/LICENSE
freefall-1.0.0b1.dist-info/METADATA
freefall-1.0.0b1.dist-info/WHEEL
freefall-1.0.0b1.dist-info/top_level.txt
freefall-1.0.0b1.dist-info/RECORD
