Metadata-Version: 2.1
Name: freefall
Version: 1.0.0b1
Summary: A Python package module for simulating falling objects with aerodynamic drag.
Home-page: https://github.com/cwstryker/freefall/
Author: Chadwick Stryker
Author-email: cwsaccts@stryker5.org
License: UNKNOWN
Platform: UNKNOWN
Classifier: Development Status :: 2 - Pre-Alpha
Classifier: Intended Audience :: Education
Classifier: License :: OSI Approved :: MIT License
Classifier: Operating System :: OS Independent
Classifier: Programming Language :: Python :: 3
Requires-Python: >=3.6
